tenkichecker.py
tenkichecker-0.1.8.dist-info/METADATA
tenkichecker-0.1.8.dist-info/WHEEL
tenkichecker-0.1.8.dist-info/top_level.txt
tenkichecker-0.1.8.dist-info/RECORD
