Metadata-Version: 2.1
Name: tenkichecker
Version: 0.1.8
Summary: Enter any prefecture name to output the place name, weather, maximum temperature, minimum temperature, and humidity as listed in Yahoo Weather
Home-page: https://github.com/gotouyamato/tenkichecker
Author: gotouyamato
Author-email: s2122100@stu.musashino-u.ac.jp
Project-URL: Bug Tracker, https://github.com/gotouyamato/tenkichecker/issues
Classifier: Programming Language :: Python :: 3
Classifier: License :: OSI Approved :: MIT License
Classifier: Operating System :: OS Independent
Requires-Python: >=3.7
Requires-Dist: selenium
Requires-Dist: bs4
